<manifest alg="2" build="2017.0.4.363" opt="false" iceEnabled="true" iceMarkupVersion="2" iceEnabledOptions="link,responsive,cachebuster,textStyling" exportTarget="other" domain="kaiphotography.com" resolutions="1x" timestamp="1503604774967">
  <folder name="css">
    <file name="site_global.css" crc="443350757"/>
    <file name="index.css" crc="194905163" ref="index"/>
    <file name="iefonts_index.css" crc="3897835293" ref="index"/>
  </folder>
  <folder name="scripts">
    <file name="jquery-1.8.3.min.js" crc="209076791" ref="index"/>
    <file name="museutils.js" crc="4216313831" ref="index"/>
    <file name="whatinput.js" crc="86476730" ref="index"/>
    <file name="museconfig.js" crc="474374037" ref="index"/>
    <file name="jquery.watch.js" crc="460461809" ref="index"/>
    <file name="webpro.js" crc="4143865194" ref="index"/>
    <file name="musewpslideshow.js" crc="3781122836" ref="index"/>
    <file name="jquery.museoverlay.js" crc="4030747646" ref="index"/>
    <file name="touchswipe.js" crc="4200445185" ref="index"/>
    <file name="jquery.musemenu.js" crc="493622299" ref="index"/>
    <file name="jquery.musepolyfill.bgsize.js" crc="4110862005" ref="index"/>
    <file name="form_check.php" crc="154010282" ref="index"/>
    <file name="form_throttle.php" crc="266437015" ref="index"/>
    <file name="form_process.php" crc="512629711" ref="index"/>
    <file name="form-u3289.php" crc="4168701703" ref="index"/>
    <file name="jquery.scrolleffects.js" crc="128250821" ref="index"/>
    <file name="html5shiv.js" crc="4241844378" ref="index"/>
    <file name="require.js" crc="3951022091" ref="index"/>
  </folder>
  <folder name="images">
    <file name="dsc_2118-01.jpg" crc="314106311" seo="true" ref="index">
      <caption webpage="index" alt=""/>
    </file>
    <file name="blank.gif" crc="4208392903" ref="index"/>
    <file name="dsc_2119-02.jpg" crc="4213592233" seo="true" ref="index">
      <caption webpage="index" alt=""/>
    </file>
    <file name="dsc_2128-02.jpg" crc="4273293181" seo="true" ref="index">
      <caption webpage="index" alt=""/>
    </file>
    <file name="dsc_2135-01.jpg" crc="93359415" seo="true" ref="index">
      <caption webpage="index" alt=""/>
    </file>
    <file name="loading.gif" crc="3815509949" ref="index"/>
    <file name="untitled-1292x173.png" crc="3937025412" seo="true" ref="index">
      <caption webpage="index" alt=""/>
    </file>
    <file name="untitled-1-u279-fr.png" crc="3915520208" ref="index"/>
    <file name="kualalumpur_streetsofkl_streetphotography_11-08-2015_smq_bw_wm-5-of-16.jpg" crc="3879875392" ref="index">
      <caption webpage="index" alt=""/>
    </file>
    <file name="l1050521.jpg" crc="107913611" ref="index">
      <caption webpage="index" alt=""/>
    </file>
    <file name="dsc_1531.jpg" crc="3784989260" seo="true" ref="index">
      <caption webpage="index" alt=""/>
    </file>
    <file name="dsc_1609.jpg" crc="4036324960" seo="true" ref="index">
      <caption webpage="index" alt=""/>
    </file>
    <file name="dsc_1612.jpg" crc="3798268330" seo="true" ref="index">
      <caption webpage="index" alt=""/>
    </file>
    <file name="dsc_1615.jpg" crc="529514932" seo="true" ref="index">
      <caption webpage="index" alt=""/>
    </file>
    <file name="dsc_1625.jpg" crc="3868396856" seo="true" ref="index">
      <caption webpage="index" alt=""/>
    </file>
    <file name="dsc_1656.jpg" crc="3919259218" seo="true" ref="index">
      <caption webpage="index" alt=""/>
    </file>
    <file name="dsc_1673.jpg" crc="202290409" seo="true" ref="index">
      <caption webpage="index" alt=""/>
    </file>
    <file name="dsc_1643s.jpg" crc="4261229358" seo="true" ref="index">
      <caption webpage="index" alt=""/>
    </file>
    <file name="dsc_0255.jpg" crc="3853413436" seo="true" ref="index">
      <caption webpage="index" alt=""/>
    </file>
    <file name="dsc_1207.jpg" crc="4069632902" seo="true" ref="index">
      <caption webpage="index" alt=""/>
    </file>
    <file name="dsc_2328.jpg" crc="148590860" seo="true" ref="index">
      <caption webpage="index" alt=""/>
    </file>
    <file name="dsc_0965.jpg" crc="445902808" seo="true" ref="index">
      <caption webpage="index" alt=""/>
    </file>
    <file name="dsc_0061.jpg" crc="4205087216" seo="true" ref="index">
      <caption webpage="index" alt=""/>
    </file>
    <file name="dsc_1156.jpg" crc="3758757816" seo="true" ref="index">
      <caption webpage="index" alt=""/>
    </file>
    <file name="dsc_1694.jpg" crc="462818405" seo="true" ref="index">
      <caption webpage="index" alt=""/>
    </file>
    <file name="dsc_2022.jpg" crc="4040736681" seo="true" ref="index">
      <caption webpage="index" alt=""/>
    </file>
    <file name="dsc_1190.jpg" crc="3992710559" seo="true" ref="index">
      <caption webpage="index" alt=""/>
    </file>
    <file name="dsc_0418.jpg" crc="4207489016" seo="true" ref="index">
      <caption webpage="index" alt=""/>
    </file>
    <file name="e34.jpg" crc="84009044" seo="true" ref="index">
      <caption webpage="index" alt=""/>
    </file>
    <file name="e67.jpg" crc="4024217513" seo="true" ref="index">
      <caption webpage="index" alt=""/>
    </file>
    <file name="e677.jpg" crc="103193451" seo="true" ref="index">
      <caption webpage="index" alt=""/>
    </file>
    <file name="dsc_2181.jpg" crc="427785338" seo="true" ref="index">
      <caption webpage="index" alt=""/>
    </file>
    <file name="dsc_1727.jpg" crc="170863419" seo="true" ref="index">
      <caption webpage="index" alt=""/>
    </file>
    <file name="dsc_1739.jpg" crc="9536941" seo="true" ref="index">
      <caption webpage="index" alt=""/>
    </file>
    <file name="dsc_1939.jpg" crc="150353781" seo="true" ref="index">
      <caption webpage="index" alt=""/>
    </file>
    <file name="dsc_1254.jpg" crc="4232299034" seo="true" ref="index">
      <caption webpage="index" alt=""/>
    </file>
    <file name="dsc_1256.jpg" crc="3804040753" seo="true" ref="index">
      <caption webpage="index" alt=""/>
    </file>
    <file name="dsc_1531-crop-u910.jpg" crc="4101212292" seo="true" ref="index">
      <caption webpage="index" alt=""/>
    </file>
    <file name="dsc_1609140x93.jpg" crc="3776326163" seo="true" ref="index">
      <caption webpage="index" alt=""/>
    </file>
    <file name="dsc_1612140x93.jpg" crc="308445967" seo="true" ref="index">
      <caption webpage="index" alt=""/>
    </file>
    <file name="dsc_1615140x93.jpg" crc="4294058783" seo="true" ref="index">
      <caption webpage="index" alt=""/>
    </file>
    <file name="dsc_1625140x93.jpg" crc="58059652" seo="true" ref="index">
      <caption webpage="index" alt=""/>
    </file>
    <file name="dsc_1656140x93.jpg" crc="4259666365" seo="true" ref="index">
      <caption webpage="index" alt=""/>
    </file>
    <file name="dsc_1673140x93.jpg" crc="4086465052" seo="true" ref="index">
      <caption webpage="index" alt=""/>
    </file>
    <file name="dsc_1643s140x93.jpg" crc="265374878" seo="true" ref="index">
      <caption webpage="index" alt=""/>
    </file>
    <file name="dsc_0255140x93.jpg" crc="74109285" seo="true" ref="index">
      <caption webpage="index" alt=""/>
    </file>
    <file name="dsc_1207140x93.jpg" crc="181008937" seo="true" ref="index">
      <caption webpage="index" alt=""/>
    </file>
    <file name="dsc_2328140x93.jpg" crc="94585376" seo="true" ref="index">
      <caption webpage="index" alt=""/>
    </file>
    <file name="dsc_0965-crop-u1444.jpg" crc="4113284325" seo="true" ref="index">
      <caption webpage="index" alt=""/>
    </file>
    <file name="dsc_0061140x93.jpg" crc="3949949066" seo="true" ref="index">
      <caption webpage="index" alt=""/>
    </file>
    <file name="dsc_1156140x93.jpg" crc="179972177" seo="true" ref="index">
      <caption webpage="index" alt=""/>
    </file>
    <file name="dsc_1694140x93.jpg" crc="146519413" seo="true" ref="index">
      <caption webpage="index" alt=""/>
    </file>
    <file name="dsc_2022140x93.jpg" crc="32847389" seo="true" ref="index">
      <caption webpage="index" alt=""/>
    </file>
    <file name="dsc_1190140x93.jpg" crc="4039416752" seo="true" ref="index">
      <caption webpage="index" alt=""/>
    </file>
    <file name="dsc_0418-crop-u1748.jpg" crc="3844943683" seo="true" ref="index">
      <caption webpage="index" alt=""/>
    </file>
    <file name="e34-crop-u1768.jpg" crc="4157822745" seo="true" ref="index">
      <caption webpage="index" alt=""/>
    </file>
    <file name="e67140x93.jpg" crc="3779279352" seo="true" ref="index">
      <caption webpage="index" alt=""/>
    </file>
    <file name="e677140x93.jpg" crc="379100311" seo="true" ref="index">
      <caption webpage="index" alt=""/>
    </file>
    <file name="dsc_2181-crop-u1849.jpg" crc="4171292667" seo="true" ref="index">
      <caption webpage="index" alt=""/>
    </file>
    <file name="dsc_1727140x93.jpg" crc="476170049" seo="true" ref="index">
      <caption webpage="index" alt=""/>
    </file>
    <file name="dsc_1739140x93.jpg" crc="493896057" seo="true" ref="index">
      <caption webpage="index" alt=""/>
    </file>
    <file name="dsc_1939140x93.jpg" crc="470695286" seo="true" ref="index">
      <caption webpage="index" alt=""/>
    </file>
    <file name="dsc_1254140x93.jpg" crc="3804341666" seo="true" ref="index">
      <caption webpage="index" alt=""/>
    </file>
    <file name="dsc_1256140x93.jpg" crc="124089605" seo="true" ref="index">
      <caption webpage="index" alt=""/>
    </file>
    <file name="kl1.jpg" crc="280957440" ref="index">
      <caption webpage="index" alt=""/>
    </file>
    <file name="1200px-canon_eos_1100d_with_canon_ef-s_18-55mm_f35-56_is_ii.jpg" crc="209463329" seo="true" ref="index">
      <caption webpage="index" alt=""/>
    </file>
    <file name="11134_000001757_8e2e_canon_1100d_build_1.jpg" crc="3855645233" seo="true" ref="index">
      <caption webpage="index" alt=""/>
    </file>
    <file name="25478_d5100_front.png" crc="208374696" seo="true" ref="index">
      <caption webpage="index" alt=""/>
    </file>
    <file name="5100 b.jpg" crc="3793883381" seo="true" ref="index">
      <caption webpage="index" alt=""/>
    </file>
    <file name="eric-kim-street-photography-black-and-white-1-seoul-2009 (1).jpg" crc="479680917" ref="index">
      <caption webpage="index" alt=""/>
    </file>
    <file name="dsc_0366.jpg" crc="161558922" seo="true" ref="index">
      <caption webpage="index" alt=""/>
    </file>
    <file name="dsc_2685-crop-u3207.jpg" crc="4169565590" seo="true" ref="index">
      <caption webpage="index" alt=""/>
    </file>
    <file name="dsc_2471.jpg" crc="44259294" seo="true" ref="index">
      <caption webpage="index" alt=""/>
    </file>
    <file name="10923842903_561c0655d1_o.jpg" crc="4063858382" ref="index">
      <caption webpage="index" alt=""/>
    </file>
    <file name="souveraen-black-silver-dark.jpg" crc="412534962" ref="index">
      <caption webpage="index" alt=""/>
    </file>
  </folder>
  <file name="index.html" crc="325404021" seo="true" mt="1503603722157" redirect="true"/>
</manifest>